BUDA/__init__.py
BUDA/app.py
BUDA/cli.py
BUDA/version.py
BUDA/models/__init__.py
BUDA/models/activity.py
BUDA/models/aptgroups.py
BUDA/models/narrative.py
BUDA/models/narratives_user_profiles.py
BUDA/models/user.py
BUDA/models/user_profiles_activity_types.py
BUDA/routes/activities.py
BUDA/routes/ai_integration.py
BUDA/routes/context.py
BUDA/routes/narrative_review.py
BUDA/routes/narratives.py
BUDA/routes/root.py
BUDA/routes/settings.py
BUDA/routes/statistics.py
BUDA/routes/user_profiles.py
BUDA/static/css/style.css
BUDA/static/images/logo.png
BUDA/static/js/scripts.js
BUDA/templates/activities.html
BUDA/templates/base.html
BUDA/templates/context.html
BUDA/templates/edit_activities.html
BUDA/templates/edit_user_profile.html
BUDA/templates/home.html
BUDA/templates/narrative_edit.html
BUDA/templates/narrative_review.html
BUDA/templates/narratives.html
BUDA/templates/settings.html
BUDA/templates/statistics.html
BUDA/templates/user_profiles.html
BUDA/utils/__init__.py
BUDA/utils/apt_ttps.py
BUDA/utils/behavior_engine.py
BUDA/utils/config_utils.py
BUDA/utils/context_utils.py
BUDA/utils/init_db_util.py
BUDA/utils/llm_utils.py
BUDA/utils/logger.py
BUDA/utils/narrative_worker.py
BUDA/utils/orchestrator.py
BUDA-1.0.0.dist-info/LICENCE
BUDA-1.0.0.dist-info/METADATA
BUDA-1.0.0.dist-info/WHEEL
BUDA-1.0.0.dist-info/entry_points.txt
BUDA-1.0.0.dist-info/top_level.txt
BUDA-1.0.0.dist-info/RECORD
