Metadata-Version: 2.1
Name: BUDA
Version: 1.0.0
Summary: Behavioral User-driven Deceptive Activities Framework
Home-page: https://github.com/Base4Security/BUDA/
Author-email: idi@base4sec.com
Project-URL: Bug Tracker, https://github.com/Base4Security/BUDA/issues
Classifier: Programming Language :: Python :: 3
Classifier: License :: OSI Approved :: GNU General Public License v3 (GPLv3)
Classifier: Topic :: Software Development :: Libraries :: Application Frameworks
Classifier: Operating System :: OS Independent
License-File: LICENCE
Requires-Dist: flask
Requires-Dist: flask-sqlalchemy
Requires-Dist: python-dotenv
Requires-Dist: requests
Requires-Dist: openai
Requires-Dist: python-evtx
Requires-Dist: pywinrm
